README.md
__init__.py
fisheye.py
image_find_charuco_corners.py
rgo_ai_tools.egg-info/PKG-INFO
rgo_ai_tools.egg-info/SOURCES.txt
rgo_ai_tools.egg-info/dependency_links.txt
rgo_ai_tools.egg-info/requires.txt
rgo_ai_tools.egg-info/top_level.txt
rgo_ai_tools-1.0.0.dist-info/METADATA
rgo_ai_tools-1.0.0.dist-info/WHEEL
rgo_ai_tools-1.0.0.dist-info/top_level.txt
rgo_ai_tools-1.0.0.dist-info/RECORD
