Metadata-Version: 2.1
Name: rgo-ai-tools
Version: 1.0.0
Summary: Imported as utils_shared. Utils that are shared between rgo ai repos
Home-page: https://bitbucket.org/rgo-tech/semanticseg/src/master/
License: UNKNOWN
Platform: UNKNOWN
Requires-Dist: PyExifTool
Requires-Dist: lxml
Requires-Dist: opencv-python
Requires-Dist: opencv-python-headless
Requires-Dist: tqdm
Requires-Dist: numpy
Requires-Dist: matplotlib
